serpapi/__init__.py
serpapi/__version__.py
serpapi/client.py
serpapi/core.py
serpapi/exceptions.py
serpapi/http.py
serpapi/models.py
serpapi/textui.py
serpapi/utils.py
serpapi-0.1.5.dist-info/LICENSE
serpapi-0.1.5.dist-info/METADATA
serpapi-0.1.5.dist-info/WHEEL
serpapi-0.1.5.dist-info/top_level.txt
serpapi-0.1.5.dist-info/RECORD
